[
  {
    "ContainingType": "PatientManagement.WebApi.Controllers.InitialConsultationController",
    "Method": "CreateInitialConsultation",
    "RelativePath": "api/InitialConsultation",
    "HttpMethod": "POST",
    "IsController": true,
    "Order": 0,
    "Parameters": [
      {
        "Name": "command",
        "Type": "PatientManagement.Application.InitialConsultation.CreateInitialConsultation.CreateInitialConsultationCommand",
        "IsRequired": true
      }
    ],
    "ReturnTypes": []
  },
  {
    "ContainingType": "PatientManagement.WebApi.Controllers.InitialConsultationController",
    "Method": "GetInitialConsultations",
    "RelativePath": "api/InitialConsultation",
    "HttpMethod": "GET",
    "IsController": true,
    "Order": 0,
    "Parameters": [],
    "ReturnTypes": []
  },
  {
    "ContainingType": "PatientManagement.WebApi.Controllers.PatientController",
    "Method": "CreatePatient",
    "RelativePath": "api/Patient",
    "HttpMethod": "POST",
    "IsController": true,
    "Order": 0,
    "Parameters": [
      {
        "Name": "command",
        "Type": "PatientManagement.Application.Patients.CreatePatient.CreatePatientCommand",
        "IsRequired": true
      }
    ],
    "ReturnTypes": []
  },
  {
    "ContainingType": "PatientManagement.WebApi.Controllers.PatientController",
    "Method": "GetPatients",
    "RelativePath": "api/Patient",
    "HttpMethod": "GET",
    "IsController": true,
    "Order": 0,
    "Parameters": [],
    "ReturnTypes": []
  },
  {
    "ContainingType": "PatientManagement.WebApi.Controllers.PeriodicEvaluationController",
    "Method": "CreatePeriodicEvaluation",
    "RelativePath": "api/PeriodicEvaluation",
    "HttpMethod": "POST",
    "IsController": true,
    "Order": 0,
    "Parameters": [
      {
        "Name": "command",
        "Type": "PatientManagement.Application.Evaluations.CreateEvaluation.CreatePeriodicEvaluationCommand",
        "IsRequired": true
      }
    ],
    "ReturnTypes": []
  },
  {
    "ContainingType": "PatientManagement.WebApi.Controllers.PeriodicEvaluationController",
    "Method": "GetPeriodicEvaluation",
    "RelativePath": "api/PeriodicEvaluation",
    "HttpMethod": "GET",
    "IsController": true,
    "Order": 0,
    "Parameters": [],
    "ReturnTypes": []
  },
  {
    "ContainingType": "PatientManagement.WebApi.Controllers.UserController",
    "Method": "CreateUser",
    "RelativePath": "api/User",
    "HttpMethod": "POST",
    "IsController": true,
    "Order": 0,
    "Parameters": [
      {
        "Name": "command",
        "Type": "PatientManagement.Application.Users.CreateUser.CreateUserCommand",
        "IsRequired": true
      }
    ],
    "ReturnTypes": []
  }
]